case_boss/__init__.py
case_boss/case_boss.py
case_boss/cli.py
case_boss/const.py
case_boss/errors.py
case_boss/py.typed
case_boss/types.py
case_boss/utils.py
case_boss/abstract/__init__.py
case_boss/abstract/case_converter.py
case_boss/converters/__init__.py
case_boss/converters/camel_converter.py
case_boss/converters/kebab_converter.py
case_boss/converters/pascal_converter.py
case_boss/converters/snake_converter.py
case_boss/converters/space_converter.py
case_boss/converters/start_converter.py
case_boss-0.1.0.dist-info/licenses/LICENSE
case_boss-0.1.0.dist-info/METADATA
case_boss-0.1.0.dist-info/WHEEL
case_boss-0.1.0.dist-info/entry_points.txt
case_boss-0.1.0.dist-info/top_level.txt
case_boss-0.1.0.dist-info/RECORD
