Metadata-Version: 2.4
Name: case-boss
Version: 0.1.0
Summary: Dict/JSON key case converter (to snake, camel, kebab, etc.) with CLI
Author: codezaur
License: MIT License
Project-URL: Homepage, https://github.com/codezaur/case-boss
Project-URL: Repository, https://github.com/codezaur/case-boss
Project-URL: Issues, https://github.com/codezaur/case-boss/issues
Keywords: json,case-conversion,case-converter,snake-case,camel-case,kebab-case,pascal-case,space-case,start-case,title-case,cli,python
Classifier: Intended Audience :: Developers
Classifier: Programming Language :: Python :: 3
Classifier: Programming Language :: Python :: 3.8
Classifier: Programming Language :: Python :: 3.9
Classifier: Programming Language :: Python :: 3.10
Classifier: Programming Language :: Python :: 3.11
Classifier: Programming Language :: Python :: 3.12
Classifier: Programming Language :: Python :: 3.13
Classifier: License :: OSI Approved :: MIT License
Classifier: Topic :: Software Development :: Libraries :: Python Modules
Classifier: Operating System :: OS Independent
Requires-Python: >=3.8
License-File: LICENSE
Provides-Extra: cli
Requires-Dist: typer>=0.17.0; extra == "cli"
Provides-Extra: dev
Requires-Dist: black; extra == "dev"
Requires-Dist: isort; extra == "dev"
Requires-Dist: flake8; extra == "dev"
Requires-Dist: mypy; extra == "dev"
Requires-Dist: pytest; extra == "dev"
Requires-Dist: pre-commit; extra == "dev"
Requires-Dist: build<2,>=1.2; extra == "dev"
Dynamic: license-file
